django_yandex_ad_manager/__init__.py
django_yandex_ad_manager/admin.py
django_yandex_ad_manager/apps.py
django_yandex_ad_manager/babel.config.json
django_yandex_ad_manager/middleware.py
django_yandex_ad_manager/models.py
django_yandex_ad_manager/package.json
django_yandex_ad_manager/postcss.config.mjs
django_yandex_ad_manager/tailwind.config.js
django_yandex_ad_manager/tests.py
django_yandex_ad_manager/webpack.config.js
django_yandex_ad_manager/migrations/0001_initial.py
django_yandex_ad_manager/migrations/0002_alter_yandexadblock_adblock_type.py
django_yandex_ad_manager/migrations/0003_yandexadblock_adblock_placeholder_action_and_more.py
django_yandex_ad_manager/migrations/0004_yandexadblock_adblock_platform_for_use.py
django_yandex_ad_manager/migrations/0005_yandexadblock_adblock_template.py
django_yandex_ad_manager/migrations/__init__.py
django_yandex_ad_manager/static/YandexAdManager/css/attention.css
django_yandex_ad_manager/static/YandexAdManager/css/index.css
django_yandex_ad_manager/static/YandexAdManager/css/index.min.css
django_yandex_ad_manager/static/YandexAdManager/css/main.js
django_yandex_ad_manager/static/YandexAdManager/img/ads.svg
django_yandex_ad_manager/static/YandexAdManager/img/yandex.svg
django_yandex_ad_manager/static/YandexAdManager/js/admanager.js
django_yandex_ad_manager/static/YandexAdManager/js/index.js
django_yandex_ad_manager/static/YandexAdManager/js/index.min.js
django_yandex_ad_manager/templates/YandexAdManager/admanager_element.html
django_yandex_ad_manager/templates/YandexAdManager/admanager_element_core.html
django_yandex_ad_manager/templates/YandexAdManager/admanager_element_default.html
django_yandex_ad_manager/templates/YandexAdManager/admanager_element_in_pagination.html
django_yandex_ad_manager/templates/YandexAdManager/admanager_element_outlined.html
django_yandex_ad_manager/templates/YandexAdManager/admanager_header.html
django_yandex_ad_manager/templates/YandexAdManager/admanager_scripts.html
django_yandex_ad_manager-0.0.8.dist-info/METADATA
django_yandex_ad_manager-0.0.8.dist-info/WHEEL
django_yandex_ad_manager-0.0.8.dist-info/licenses/LICENCE
django_yandex_ad_manager-0.0.8.dist-info/RECORD
