Metadata-Version: 2.4
Name: django-yandex-ad-manager
Version: 0.0.8
Summary: This package allows you to easily integrate advertising blocks from the Yandex Advertising Network onto any website built using the Django framework.
Project-URL: Complete guide RU, https://timthewebmaster.com/ru/tools/django-yandex-ad-manager/
Project-URL: Complete guide EN, https://timthewebmaster.com/en/tools/django-yandex-ad-manager/
Project-URL: Repository, https://github.com/DmRafaule/django-yandex-ad-manager
Author-email: Tim The Webmaster <timachuduk@gmail.com>
License-Expression: MIT
License-File: LICENCE
Keywords: ads,advertisement network,django,django app,timthewebmaster,yandex
Classifier: Development Status :: 3 - Alpha
Classifier: Environment :: Plugins
Classifier: Environment :: Web Environment
Classifier: Framework :: Django
Classifier: Intended Audience :: Developers
Classifier: Intended Audience :: Education
Classifier: License :: OSI Approved :: GNU General Public License v3 (GPLv3)
Classifier: Natural Language :: English
Classifier: Natural Language :: Russian
Classifier: Operating System :: OS Independent
Classifier: Programming Language :: JavaScript
Classifier: Programming Language :: Python :: 3
Classifier: Topic :: Internet :: WWW/HTTP :: Dynamic Content
Classifier: Topic :: Internet :: WWW/HTTP :: Dynamic Content :: Content Management System
Classifier: Topic :: Internet :: WWW/HTTP :: WSGI
Classifier: Topic :: Software Development :: Pre-processors
Requires-Python: >=3.10
Requires-Dist: django>=5.1.7
